ysdb/Wrapper.py
ysdb/__init__.py
ysdb/ysdbLib.py
ysdb/debian/__init__.py
ysdb/debian/libIce.so.35
ysdb/debian/libIceUtil.so.35
ysdb/debian/libQt5Core.so.5
ysdb/debian/libQt5Network.so.5
ysdb/debian/libQt5Test.so.5
ysdb/debian/libicudata.so.56
ysdb/debian/libicui18n.so.56
ysdb/debian/libicuuc.so.56
ysdb/debian/libysLib.so
ysdb/debian/libysLib.so.1
ysdb/debian/libysdbLib.so
ysdb/debian/libysdbLib.so.1
ysdb/win/Qt5CLucene.dll
ysdb/win/Qt5Concurrent.dll
ysdb/win/Qt5Core.dll
ysdb/win/Qt5DBus.dll
ysdb/win/Qt5Help.dll
ysdb/win/Qt5Network.dll
ysdb/win/Qt5Script.dll
ysdb/win/Qt5Test.dll
ysdb/win/__init__.py
ysdb/win/bzip2.dll
ysdb/win/ice35.dll
ysdb/win/iceutil35.dll
ysdb/win/msvcp120.dll
ysdb/win/msvcr120.dll
ysdb/win/ysLib.dll
ysdb/win/ysdbLib.dll
ysdb/win/zlib.dll
ysdb/win/zlib1.dll
ysdb_linux-0.1.13.dist-info/METADATA
ysdb_linux-0.1.13.dist-info/WHEEL
ysdb_linux-0.1.13.dist-info/top_level.txt
ysdb_linux-0.1.13.dist-info/RECORD
